{
  "title": "Sobre Nosotros",
  "content": "Esta es una p치gina de ejemplo sobre nosotros.",
  "items": [
    { "name": "Elemento 1 que es diferente del index.hbs", "description": "Descripci칩n del elemento 1 que es diferente del index.hbs" },
    { "name": "Elemento 2 que es diferente del index.hbs", "description": "Descripci칩n del elemento 2 que es diferente del index.hbs" },
    { "name": "Elemento 3 que es diferente del index.hbs", "description": "Descripci칩n del elemento 3 que es diferente del index.hbs" }
  ],
  "test-each-items": [
    { "name": "Test each item 1 del about" },
    { "name": "Test each item 2 del about" },
    { "name": "Test each item 3 del about" }
  ]
}